setup.py
openid_teams/__init__.py
openid_teams/teams.py
python_openid_teams.egg-info/PKG-INFO
python_openid_teams.egg-info/SOURCES.txt
python_openid_teams.egg-info/dependency_links.txt
python_openid_teams.egg-info/requires.txt
python_openid_teams.egg-info/top_level.txt
python_openid_teams.egg-info/zip-safe