Metadata-Version: 1.0
Name: python-openid-teams
Version: 1.0
Summary: This is an implementation of the OpenID teams extension for python-openid
Home-page: http://www.github.com/puiterwijk/python-openid-teams/
Author: Patrick Uiterwijk
Author-email: puiterwijk@gmail.com
License: BSD
Keywords: openid teams
Platform: UNKNOWN
